{
  "langs": {
    "fr": [
      "ui",
      "abbrevs"
    ],
    "it": [
      "ui",
      "abbrevs"
    ]
  },
  "courts": {
    "ager": {
      "name": "Arbeitsgericht",
      "ABBREV": "AGer %s"
    },
    "anwaltsaufsichtsbehörde": {
      "name": "Anwaltsaufsichtsbehörde"
    },
    "anwaltsaufsichtskommission": {
      "name": "Anwaltsaufsichtskommission"
    },
    "anwaltskammer": {
      "name": "Anwaltskammer"
    },
    "anwaltskommission": {
      "name": "Anwaltskommission"
    },
    "appger": {
      "name": "Appellationsgericht",
      "ABBREV": "AppGer %s"
    },
    "baurekurskommission": {
      "name": "Baurekurskommission"
    },
    "bezger": {
      "name": "Bezirksgericht",
      "ABBREV": "BezGer %s"
    },
    "bodenverbesserungskommission": {
      "name": "Bodenverbesserungskommission"
    },
    "cour.de.cassation": {
      "name": "Cour de cassation"
    },
    "cour.de.cassation.civile": {
      "name": "Cour de cassation civile"
    },
    "cour.de.cassation.penale": {
      "name": "Cour de cassation pénale"
    },
    "enteignungsschätzungskommission": {
      "name": "Enteignungsschätzungskommission"
    },
    "entger": {
      "name": "Enteignungsgericht",
      "ABBREV": "EntGer %s"
    },
    "friedensrichteramt": {
      "name": "Friedensrichteramt"
    },
    "fu-gericht": {
      "name": "Gericht für fürsorgerische Unterbringungen",
      "ABBREV": "FU-Gericht %s"
    },
    "hger": {
      "name": "Handelsgericht",
      "ABBREV": "HGer %s"
    },
    "kassationsgericht": {
      "name": "Kassationsgericht"
    },
    "kger": {
      "name": "Kantonsgericht",
      "ABBREV": "KGer %s"
    },
    "kindesunderwachsenenschutzgericht": {
      "name": "Kindes- und Erwachsenenschutzgericht"
    },
    "jugendgericht": {
      "name": "Jugendgericht"
    },
    "oger": {
      "name": "Obergericht",
      "ABBREV": "OGer %s"
    },
    "regionalgericht": {
      "name": "Regionalgericht"
    },
    "rekurskommissionbostadel": {
      "name": "Rekurskommission Bostadel"
    },
    "rkmf": {
      "name": "Rekurskommission für Massnahmen gegenüber Fahrzeugführerinnen und Fahrzeugführern",
      "ABBREV": "RKMF %s"
    },
    "schkk": {
      "name": "Schuldbetreibungs- und Konkurskommission",
      "ABBREV": "SchKK %s"
    },
    "schlichtungsbehörde": {
      "name": "Schlichtungsbehörde"
    },
    "schlichtungsbehördemieteundpacht": {
      "name": "Schlichtungsbehörde für Miete und Pacht"
    },
    "schlichtungsstellediskriminierung": {
      "name": "Schlichtungsstelle bei Diskriminierung im Erwerbsleben"
    },
    "schlichtungsstellefrauundmann": {
      "name": "Schlichtungsstelle Gleichstellung von Frau und Mann"
    },
    "schlichtungsstellegleichstellungsfragen": {
      "name": "Schlichtungsstelle für Gleichstellungsfragen"
    },
    "schlichtungsstellemiete": {
      "name": "Schlichtungsstelle Mietverhältnisse"
    },
    "schlichtungsstellemieteundnichtlandwirtschftlichepacht": {
      "name": "Schlichtungsstelle für Miete und nichtlandwirtschaftliche Pacht"
    },
    "sozialversicherungsgericht": {
      "name": "Sozialversicherungsgericht"
    },
    "spezialverwaltungsgericht": {
      "name": "Spezialverwaltungsgericht"
    },
    "steuerrekurskommission": {
      "name": "Steuerrekurskommission"
    },
    "stger": {
      "name": "Steuergericht",
      "ABBREV": "StGer %s"
    },
    "strafgericht": {
      "name": "Strafgericht"
    },
    "tribunal.cantonal": {
      "name": "Tribunal cantonal"
    },
    "tribunale.d.appello": {
      "name": "Tribunale d'appello"
    },
    "vermittler": {
      "name": "Vermittler"
    },
    "vger": {
      "name": "Verwaltungsgericht",
      "ABBREV": "VGer %s"
    },
    "wirtschaftsstrafgericht": {
      "name": "Wirtschaftsstrafgericht"
    },
    "zivilgericht": {
      "name": "Zivilgericht"
    },
    "zivilkreisgericht": {
      "name": "Zivilkreisgericht"
    },
    "zwangsmassnahmengericht": {
      "name": "Zwangsmassnahmengericht"
    },
    "bger": {
      "name": "Schweizerisches Bundesgericht",
      "ABBREV": "BGer",
      "variants": {
        "fr": {
          "abbrev": "TF"
        },
        "it": {
          "abbrev": "TF"
        }
      }
    },
    "bpatger": {
      "name": "Schweizerisches Bundespatentgericht",
      "ABBREV": "BPatGer",
      "variants": {
        "fr": {
          "abbrev": "TFB"
        },
        "it": {
          "abbrev": "TFB"
        }
      }
    },
    "bstger": {
      "name": "Schweizerisches Bundesstrafgericht",
      "ABBREV": "BStGer",
      "variants": {
        "fr": {
          "abbrev": "TPF"
        },
        "it": {
          "abbrev": "TPF"
        }
      }
    },
    "bvger": {
      "name": "Schweizerisches Bundesverwaltungsgericht",
      "ABBREV": "BVGer",
      "variants": {
        "fr": {
          "abbrev": "TAF"
        },
        "it": {
          "abbrev": "TAF"
        }
      }
    },
    "evg": {
      "name": "Eidgenössisches Versicherungsgericht",
      "ABBREV": "EVG",
      "variants": {
        "fr": {
          "abbrev": "TFA"
        },
        "it": {
          "abbrev": "TFA"
        }
      }
    }
  },
  "jurisdictions": {
    "ch": {
      "name": "Switzerland",
      "courts": {
        "bger": {},
        "bstger": {},
        "bvger": {},
        "bpatger": {},
        "evg": {}
      }
    },
    "ch:ag": {
      "name": "Aargau",
      "ABBREV": "AG",
      "courts": {
        "anwaltskommission": {},
        "oger": {},
        "schkk": {},
        "schlichtungsstellegleichstellungsfragen": {},
        "spezialverwaltungsgericht": {},
        "zwangsmassnahmengericht": {}
      }
    },
    "ch:ag:aarau": {
      "name": "Aarau",
      "courts": {
        "bezger": {},
        "schlichtungsbehördemieteundpacht": {}
      }
    },
    "ch:ag:baden": {
      "name": "Baden",
      "courts": {
        "bezger": {},
        "schlichtungsbehördemieteundpacht": {}
      }
    },
    "ch:ag:bremgarten": {
      "name": "Bremgarten",
      "courts": {
        "bezger": {},
        "schlichtungsbehördemieteundpacht": {}
      }
    },
    "ch:ag:brugg": {
      "name": "Brugg",
      "courts": {
        "bezger": {},
        "schlichtungsbehördemieteundpacht": {}
      }
    },
    "ch:ag:kulm": {
      "name": "Kulm",
      "courts": {
        "bezger": {},
        "schlichtungsbehördemieteundpacht": {}
      }
    },
    "ch:ag:laufenburg": {
      "name": "Laufenburg",
      "courts": {
        "bezger": {},
        "schlichtungsbehördemieteundpacht": {}
      }
    },
    "ch:ag:lenzburg": {
      "name": "Lenzburg",
      "courts": {
        "bezger": {},
        "schlichtungsbehördemieteundpacht": {}
      }
    },
    "ch:ag:muri": {
      "name": "Muri",
      "courts": {
        "bezger": {},
        "schlichtungsbehördemieteundpacht": {}
      }
    },
    "ch:ag:rheinfelden": {
      "name": "Rheinfelden",
      "courts": {
        "bezger": {},
        "schlichtungsbehördemieteundpacht": {}
      }
    },
    "ch:ag:zofingen": {
      "name": "Zofingen",
      "courts": {
        "bezger": {},
        "schlichtungsbehördemieteundpacht": {}
      }
    },
    "ch:ag:zurzach": {
      "name": "Zurzach",
      "courts": {
        "bezger": {},
        "schlichtungsbehördemieteundpacht": {}
      }
    },
    "ch:ai": {
      "name": "Appenzell-Innerrhoden",
      "ABBREV": "AI",
      "courts": {
        "anwaltskammer": {},
        "bezger": {},
        "jugendgericht": {},
        "kger": {},
        "schlichtungsstellefrauundmann": {},
        "schlichtungsstellemiete": {},
        "vermittler": {},
        "zwangsmassnahmengericht": {}
      }
    },
    "ch:ar": {
      "name": "Appenzell-Ausserrhoden",
      "ABBREV": "AR",
      "courts": {
        "anwaltsaufsichtskommission": {},
        "kger": {},
        "oger": {},
        "schlichtungsstellediskriminierung": {},
        "schlichtungsstellemieteundnichtlandwirtschftlichepacht": {}
      }
    },
    "ch:ar:appenzeller-hinterland": {
      "name": "Appenzeller-Hinterland",
      "courts": {
        "vermittler": {}
      }
    },
    "ch:ar:appenzeller-mittelland": {
      "name": "Appenzeller-Mittelland",
      "courts": {
        "vermittler": {}
      }
    },
    "ch:ar:appenzeller-vorderland": {
      "name": "Appenzeller-Vorderland",
      "courts": {
        "vermittler": {}
      }
    },
    "ch:be": {
      "name": "Bern",
      "ABBREV": "BE",
      "courts": {
        "anwaltsaufsichtsbehörde": {},
        "bodenverbesserungskommission": {},
        "enteignungsschätzungskommission": {},
        "hger": {},
        "kindesunderwachsenenschutzgericht": {},
        "jugendgericht": {},
        "oger": {},
        "rkmf": {},
        "vger": {},
        "wirtschaftsstrafgericht": {},
        "zwangsmassnahmengericht": {}
      }
    },
    "ch:be:berner.jura-seeland": {
      "name": "Berner Jura-Seeland",
      "courts": {
        "regionalgericht": {},
        "schlichtungsbehörde": {},
        "zwangsmassnahmengericht": {}
      }
    },
    "ch:be:emmental-oberaargau": {
      "name": "Emmental-Oberaargau",
      "courts": {
        "regionalgericht": {},
        "schlichtungsbehörde": {},
        "zwangsmassnahmengericht": {}
      }
    },
    "ch:be:bern-mittelland": {
      "name": "Bern-Mittelland",
      "courts": {
        "regionalgericht": {},
        "schlichtungsbehörde": {}
      }
    },
    "ch:be:oberland": {
      "name": "Oberland",
      "courts": {
        "regionalgericht": {},
        "schlichtungsbehörde": {},
        "zwangsmassnahmengericht": {}
      }
    },
    "ch:bl": {
      "name": "Basel-Landschaft",
      "ABBREV": "BL",
      "courts": {
        "entger": {},
        "friedensrichteramt": {},
        "kger": {},
        "jugendgericht": {},
        "stger": {},
        "strafgericht": {},
        "zwangsmassnahmengericht": {}
      }
    },
    "ch:bl:basel-landschaft.ost": {
      "name": "Basel-Landschaft Ost",
      "courts": {
        "zivilkreisgericht": {}
      }
    },
    "ch:bl:basel-landschaft.west": {
      "name": "Basel-Landschaft West",
      "courts": {
        "zivilkreisgericht": {}
      }
    },
    "ch:bs": {
      "name": "Basel-Stadt",
      "ABBREV": "BS",
      "courts": {
        "anwaltsaufsichtskommission": {},
        "appger": {},
        "baurekurskommission": {},
        "fu-gericht": {},
        "jugendgericht": {},
        "rekurskommissionbostadel": {},
        "steuerrekurskommission": {},
        "strafgericht": {},
        "sozialversicherungsgericht": {},
        "zivilgericht": {}
      }
    },
    "ch:fr": {
      "name": "Fribourg",
      "ABBREV": "FR",
      "courts": {
        "tribunal.cantonal": {}
      }
    },
    "ch:ge": {
      "name": "Geneva",
      "courts": {
        "cour.de.cassation": {}
      }
    },
    "ch:glarus": {
      "name": "Glarus",
      "courts": {
        "oger": {}
      }
    },
    "ch:ju": {
      "name": "Jura",
      "courts": {
        "tribunal.cantonal": {}
      }
    },
    "ch:lu": {
      "name": "Luzern",
      "courts": {
        "oger": {}
      }
    },
    "ch:ne": {
      "name": "Neuchatel",
      "courts": {
        "cour.de.cassation.civile": {},
        "cour.de.cassation.penale": {}
      }
    },
    "ch:nw": {
      "name": "Nidwalden",
      "courts": {
        "oger": {}
      }
    },
    "ch:ow": {
      "name": "Obwalden",
      "courts": {
        "oger": {}
      }
    },
    "ch:sh": {
      "name": "Schaffhausen",
      "courts": {
        "oger": {}
      }
    },
    "ch:sz": {
      "name": "Schwyz",
      "courts": {
        "kger": {}
      }
    },
    "ch:so": {
      "name": "Solothurn",
      "courts": {
        "oger": {}
      }
    },
    "ch:sg": {
      "name": "St-Gallen",
      "courts": {
        "kger": {},
        "kassationsgericht": {}
      }
    },
    "ch:tg": {
      "name": "Thurgau",
      "courts": {
        "oger": {}
      }
    },
    "ch:ti": {
      "name": "Ticino",
      "courts": {
        "tribunale.d.appello": {}
      }
    },
    "ch:ur": {
      "name": "Uri",
      "courts": {
        "oger": {}
      }
    },
    "ch:vs": {
      "name": "Valais",
      "courts": {
        "tribunal.cantonal": {}
      }
    },
    "ch:vd": {
      "name": "Vaud",
      "courts": {
        "tribunal.cantonal": {}
      }
    },
    "ch:zg": {
      "name": "Zug",
      "courts": {
        "oger": {}
      }
    },
    "ch:zh": {
      "name": "Zurich",
      "courts": {
        "kassationsgericht": {},
        "oger": {}
      }
    }
  }
}
